foi/__init__.py
foi/__main__.py
foi/args/Args.py
foi/args/__init__.py
foi/output/Output.py
foi/output/__init__.py
foi/search/Search.py
foi/search/__init__.py
foi/util/Util.py
foi/util/__init__.py
foi-1.0.0.dist-info/METADATA
foi-1.0.0.dist-info/WHEEL
foi-1.0.0.dist-info/entry_points.txt
foi-1.0.0.dist-info/top_level.txt
foi-1.0.0.dist-info/RECORD
