Metadata-Version: 2.1
Name: foi
Version: 1.0.0
Summary: files of interest (foi) - Identifies files based on their file type
Home-page: https://github.com/npdep/foi
Author: npdep
Classifier: Operating System :: OS Independent 
Classifier: Programming Language :: Python :: 3 
